py_school_match/__init__.py
py_school_match/algorithms/__init__.py
py_school_match/algorithms/abstract_matching_algorithm.py
py_school_match/algorithms/da.py
py_school_match/algorithms/da_mtb.py
py_school_match/algorithms/da_stb.py
py_school_match/algorithms/mnsic.py
py_school_match/algorithms/msic.py
py_school_match/algorithms/nsic.py
py_school_match/algorithms/pi.py
py_school_match/algorithms/sic.py
py_school_match/algorithms/ttc.py
py_school_match/entities/__init__.py
py_school_match/entities/characteristic.py
py_school_match/entities/criteria.py
py_school_match/entities/rule.py
py_school_match/entities/ruleset.py
py_school_match/entities/school.py
py_school_match/entities/slot.py
py_school_match/entities/social_planner.py
py_school_match/entities/student.py
py_school_match/entities/student_queue.py
py_school_match/util/__init__.py
py_school_match/util/display_info.py
py_school_match/util/file_util.py
py_school_match/util/simulate_characteristics.py
py_school_match/util/simulate_preferences.py
py_school_match/util/stat.py
py_school_match-0.2.0.dist-info/DESCRIPTION.rst
py_school_match-0.2.0.dist-info/METADATA
py_school_match-0.2.0.dist-info/RECORD
py_school_match-0.2.0.dist-info/WHEEL
py_school_match-0.2.0.dist-info/metadata.json
py_school_match-0.2.0.dist-info/top_level.txt
