Metadata-Version: 2.0
Name: py-school-match
Version: 0.2.0
Summary: Py-school-match, a Python package that implements matching algorithms for the student-to-school assignation problem.
Home-page: https://github.com/igarizio/py-school-match
Author: Iacopo Garizio
Author-email: info@iacopogarizio.com
License: GLP v3
Platform: UNKNOWN
